{
  "symbol": "MA",
  "trained_at": "2026-04-22T15:30:54.964850",
  "feature_names": [
    "ret_1d",
    "ret_2d",
    "ret_3d",
    "ret_5d",
    "ret_10d",
    "ret_21d",
    "ret_63d",
    "ma5_ratio",
    "ma10_ratio",
    "ma20_ratio",
    "ma50_ratio",
    "ma100_ratio",
    "ma200_ratio",
    "ma5_20_xover",
    "ma20_50_xover",
    "ma50_200_xover",
    "rsi_14",
    "rsi_28",
    "macd_norm",
    "macd_sig",
    "macd_hist",
    "bb_pct_b",
    "bb_bw",
    "atr_ratio",
    "stoch_k",
    "stoch_d",
    "stoch_kd",
    "williams_r",
    "cci",
    "vol_ratio_5",
    "vol_ratio_20",
    "vol_trend",
    "pos_52w_high",
    "pos_52w_low",
    "vol_5d",
    "vol_21d",
    "vol_63d",
    "vol_regime",
    "mom_accel_5",
    "mom_accel_21",
    "roc_10d",
    "roc_30d",
    "roc_60d",
    "rvol_10",
    "rvol_50",
    "obv_trend",
    "vpt_trend",
    "ichi_tk_ratio",
    "ichi_cloud_width",
    "ichi_price_vs_cloud",
    "pivot_dist",
    "candle_body_ratio",
    "upper_wick_ratio",
    "lower_wick_ratio",
    "hl_range_norm",
    "hl_range_5d_avg",
    "gap_up",
    "gap_down",
    "var_ratio_10d",
    "var_ratio_21d",
    "autocorr_1d",
    "autocorr_5d",
    "autocorr_10d",
    "dist_high_20d",
    "dist_low_20d",
    "dist_high_50d",
    "dist_low_50d",
    "day_of_week",
    "month",
    "quarter",
    "month_sin",
    "month_cos",
    "dow_sin",
    "dow_cos",
    "earnings_proxy",
    "earnings_proxy_cos",
    "alpha_5d",
    "alpha_21d",
    "alpha_63d",
    "beta_63d",
    "rs_spy_20",
    "spy_ma20_ratio",
    "spy_ma50_ratio",
    "spy_ma200_ratio",
    "vix_level",
    "vix_ma20_dev",
    "vix_ret_5d",
    "high_fear",
    "low_fear",
    "fund_pe_ratio",
    "fund_forward_pe",
    "fund_peg_ratio",
    "fund_pb_ratio",
    "fund_ps_ratio",
    "fund_ev_ebitda",
    "fund_profit_margin",
    "fund_oper_margin",
    "fund_roe",
    "fund_roa",
    "fund_gross_margin",
    "fund_rev_growth",
    "fund_earn_growth",
    "fund_earn_qtr_growth",
    "fund_debt_to_equity",
    "fund_current_ratio",
    "analyst_upside",
    "analyst_range_pct",
    "analyst_sentiment",
    "short_interest",
    "days_to_earnings",
    "earnings_proximity",
    "earnings_beat_rate",
    "last_earnings_beat",
    "earnings_surprise_pct",
    "options_atm_iv",
    "options_put_call_ratio",
    "options_call_put_vol",
    "options_max_pain_diff",
    "options_iv_skew",
    "sent_vix_momentum_5d",
    "sent_sector_dispersion_21d",
    "sent_avg_sector_momentum",
    "sent_dollar_momentum_21d",
    "sent_treasury_10y_level",
    "sent_treasury_10y_momentum_21d",
    "sent_yield_curve_spread",
    "sent_put_call_ratio",
    "sent_put_call_ma20",
    "sent_news_mean",
    "sent_news_std",
    "sent_news_positive_ratio",
    "sent_news_volume",
    "sent_news_trend",
    "sent_news_volume_trend",
    "sent_fear_greed",
    "sent_fear_greed_momentum",
    "regime_vs_50ma",
    "regime_vs_200ma",
    "regime_mom63",
    "regime_mom21",
    "regime_vol_ratio",
    "regime_spy_vs_200ma",
    "regime_spy_mom63",
    "regime_vix_norm",
    "snap_is_bull",
    "snap_is_bear",
    "snap_score_norm"
  ],
  "calibration": {
    "3 Day": {
      "mean_abs_err": 0.021506163383247175,
      "std_abs_err": 0.022574996643285262,
      "dir_acc": 0.579719387755102,
      "pred_std_p50": 0.005811336567510216,
      "pred_std_p90": 0.013869569664923908,
      "n_models": 9,
      "n_dropped": 4,
      "avg_member_acc": 0.571712652249565,
      "target_mean": 0.0020477677672315936,
      "target_std": 0.0287218747240561,
      "target_p05": -0.044242694639284125,
      "target_p95": 0.04121895060882619,
      "target_max_abs": 0.25815550810592663
    },
    "1 Week": {
      "mean_abs_err": 0.026951303426577474,
      "std_abs_err": 0.027902400404415863,
      "dir_acc": 0.5959079283887468,
      "pred_std_p50": 0.007888291464833566,
      "pred_std_p90": 0.015263686473117396,
      "n_models": 9,
      "n_dropped": 4,
      "avg_member_acc": 0.5585518102372036,
      "target_mean": 0.0034422039178748096,
      "target_std": 0.03612733920918232,
      "target_p05": -0.05769872941571798,
      "target_p95": 0.053032032734935244,
      "target_max_abs": 0.244612506619921
    },
    "1 Month": {
      "mean_abs_err": 0.06920339182722003,
      "std_abs_err": 0.054398532313566346,
      "dir_acc": 0.7055412371134021,
      "pred_std_p50": 0.20581520910837836,
      "pred_std_p90": 0.314232385571715,
      "n_models": 11,
      "n_dropped": 2,
      "avg_member_acc": 0.5388078902229845,
      "target_mean": 0.014319979391821822,
      "target_std": 0.06464115895788426,
      "target_p05": -0.08518557066879505,
      "target_p95": 0.10790266852275573,
      "target_max_abs": 0.5133803231528267
    },
    "1 Quarter": {
      "mean_abs_err": 0.0864214700085456,
      "std_abs_err": 0.06133125488254683,
      "dir_acc": 0.6842105263157895,
      "pred_std_p50": 0.1054186208698061,
      "pred_std_p90": 0.15649892115077788,
      "n_models": 12,
      "n_dropped": 1,
      "avg_member_acc": 0.5918918918918918,
      "target_mean": 0.04202497392094279,
      "target_std": 0.09313210412169771,
      "target_p05": -0.12001044470747883,
      "target_p95": 0.17872778133403008,
      "target_max_abs": 0.4053363322942465
    },
    "1 Year": {
      "mean_abs_err": 0.09412567724108631,
      "std_abs_err": 0.07314774412759759,
      "dir_acc": 0.8252923976608187,
      "pred_std_p50": 0.23429791656896187,
      "pred_std_p90": 0.32371609958455,
      "n_models": 12,
      "n_dropped": 1,
      "avg_member_acc": 0.6363636363636365,
      "target_mean": 0.1674714747919087,
      "target_std": 0.1623286673156286,
      "target_p05": -0.08498498680437182,
      "target_p95": 0.46774892754961706,
      "target_max_abs": 0.5635057583265896
    }
  },
  "horizons": [
    "3 Day",
    "1 Week",
    "1 Month",
    "1 Quarter",
    "1 Year"
  ],
  "training_version": 3
}