{
  "symbol": "SHW",
  "trained_at": "2026-04-22T15:41:12.641897",
  "feature_names": [
    "ret_1d",
    "ret_2d",
    "ret_3d",
    "ret_5d",
    "ret_10d",
    "ret_21d",
    "ret_63d",
    "ma5_ratio",
    "ma10_ratio",
    "ma20_ratio",
    "ma50_ratio",
    "ma100_ratio",
    "ma200_ratio",
    "ma5_20_xover",
    "ma20_50_xover",
    "ma50_200_xover",
    "rsi_14",
    "rsi_28",
    "macd_norm",
    "macd_sig",
    "macd_hist",
    "bb_pct_b",
    "bb_bw",
    "atr_ratio",
    "stoch_k",
    "stoch_d",
    "stoch_kd",
    "williams_r",
    "cci",
    "vol_ratio_5",
    "vol_ratio_20",
    "vol_trend",
    "pos_52w_high",
    "pos_52w_low",
    "vol_5d",
    "vol_21d",
    "vol_63d",
    "vol_regime",
    "mom_accel_5",
    "mom_accel_21",
    "roc_10d",
    "roc_30d",
    "roc_60d",
    "rvol_10",
    "rvol_50",
    "obv_trend",
    "vpt_trend",
    "ichi_tk_ratio",
    "ichi_cloud_width",
    "ichi_price_vs_cloud",
    "pivot_dist",
    "candle_body_ratio",
    "upper_wick_ratio",
    "lower_wick_ratio",
    "hl_range_norm",
    "hl_range_5d_avg",
    "gap_up",
    "gap_down",
    "var_ratio_10d",
    "var_ratio_21d",
    "autocorr_1d",
    "autocorr_5d",
    "autocorr_10d",
    "dist_high_20d",
    "dist_low_20d",
    "dist_high_50d",
    "dist_low_50d",
    "day_of_week",
    "month",
    "quarter",
    "month_sin",
    "month_cos",
    "dow_sin",
    "dow_cos",
    "earnings_proxy",
    "earnings_proxy_cos",
    "alpha_5d",
    "alpha_21d",
    "alpha_63d",
    "beta_63d",
    "rs_spy_20",
    "spy_ma20_ratio",
    "spy_ma50_ratio",
    "spy_ma200_ratio",
    "vix_level",
    "vix_ma20_dev",
    "vix_ret_5d",
    "high_fear",
    "low_fear",
    "fund_pe_ratio",
    "fund_forward_pe",
    "fund_peg_ratio",
    "fund_pb_ratio",
    "fund_ps_ratio",
    "fund_ev_ebitda",
    "fund_profit_margin",
    "fund_oper_margin",
    "fund_roe",
    "fund_roa",
    "fund_gross_margin",
    "fund_rev_growth",
    "fund_earn_growth",
    "fund_earn_qtr_growth",
    "fund_debt_to_equity",
    "fund_current_ratio",
    "analyst_upside",
    "analyst_range_pct",
    "analyst_sentiment",
    "short_interest",
    "days_to_earnings",
    "earnings_proximity",
    "earnings_beat_rate",
    "last_earnings_beat",
    "earnings_surprise_pct",
    "options_atm_iv",
    "options_put_call_ratio",
    "options_call_put_vol",
    "options_max_pain_diff",
    "options_iv_skew",
    "sent_vix_momentum_5d",
    "sent_sector_dispersion_21d",
    "sent_avg_sector_momentum",
    "sent_dollar_momentum_21d",
    "sent_treasury_10y_level",
    "sent_treasury_10y_momentum_21d",
    "sent_yield_curve_spread",
    "sent_put_call_ratio",
    "sent_put_call_ma20",
    "sent_news_mean",
    "sent_news_std",
    "sent_news_positive_ratio",
    "sent_news_volume",
    "sent_news_trend",
    "sent_news_volume_trend",
    "sent_fear_greed",
    "sent_fear_greed_momentum",
    "regime_vs_50ma",
    "regime_vs_200ma",
    "regime_mom63",
    "regime_mom21",
    "regime_vol_ratio",
    "regime_spy_vs_200ma",
    "regime_spy_mom63",
    "regime_vix_norm",
    "snap_is_bull",
    "snap_is_bear",
    "snap_score_norm"
  ],
  "calibration": {
    "3 Day": {
      "mean_abs_err": 0.02079597725084195,
      "std_abs_err": 0.020688466955327958,
      "dir_acc": 0.5727040816326531,
      "pred_std_p50": 0.008606304251094326,
      "pred_std_p90": 0.02232468654600192,
      "n_models": 7,
      "n_dropped": 6,
      "avg_member_acc": 0.5190156599552572,
      "target_mean": 0.0015834500586464652,
      "target_std": 0.028030612252625747,
      "target_p05": -0.042692936815821605,
      "target_p95": 0.04409329404839388,
      "target_max_abs": 0.24757237252844505
    },
    "1 Week": {
      "mean_abs_err": 0.026882395984810712,
      "std_abs_err": 0.0262772012124698,
      "dir_acc": 0.5741687979539642,
      "pred_std_p50": 0.007957322888573246,
      "pred_std_p90": 0.015835111286158058,
      "n_models": 9,
      "n_dropped": 4,
      "avg_member_acc": 0.5378277153558053,
      "target_mean": 0.0025944212146817376,
      "target_std": 0.03530709305984012,
      "target_p05": -0.053171441911668414,
      "target_p95": 0.05538562341068541,
      "target_max_abs": 0.26149633475833844
    },
    "1 Month": {
      "mean_abs_err": 0.062120357802598704,
      "std_abs_err": 0.05018886823563638,
      "dir_acc": 0.5882731958762887,
      "pred_std_p50": 0.015958745893053343,
      "pred_std_p90": 0.020597623713904004,
      "n_models": 7,
      "n_dropped": 6,
      "avg_member_acc": 0.5040431266846361,
      "target_mean": 0.009770281950492784,
      "target_std": 0.07262264170222457,
      "target_p05": -0.1240107431820653,
      "target_p95": 0.11726316069076127,
      "target_max_abs": 0.36574455574193027
    },
    "1 Quarter": {
      "mean_abs_err": 0.09395210879103656,
      "std_abs_err": 0.05709841173106197,
      "dir_acc": 0.7328947368421053,
      "pred_std_p50": 0.25637899465262115,
      "pred_std_p90": 0.36644324801944106,
      "n_models": 5,
      "n_dropped": 8,
      "avg_member_acc": 0.5075675675675676,
      "target_mean": 0.029068236124736396,
      "target_std": 0.11311771156545267,
      "target_p05": -0.16127454879117642,
      "target_p95": 0.1936338100470015,
      "target_max_abs": 0.38647338094594724
    },
    "1 Year": {
      "mean_abs_err": 0.27237851821438663,
      "std_abs_err": 0.14895336749666552,
      "dir_acc": 0.27046783625730997,
      "pred_std_p50": 0.37987985937832675,
      "pred_std_p90": 0.5814149961922308,
      "n_models": 5,
      "n_dropped": 8,
      "avg_member_acc": 0.2517482517482518,
      "target_mean": 0.13209801270908003,
      "target_std": 0.19904889556298097,
      "target_p05": -0.2595080214840233,
      "target_p95": 0.4090686737704455,
      "target_max_abs": 0.6236116603294076
    }
  },
  "horizons": [
    "3 Day",
    "1 Week",
    "1 Month",
    "1 Quarter",
    "1 Year"
  ],
  "training_version": 3
}